forch/__init__.py
forch/tensor.py
forch-0.0.0.dist-info/METADATA
forch-0.0.0.dist-info/WHEEL
forch-0.0.0.dist-info/top_level.txt
forch-0.0.0.dist-info/RECORD
