Metadata-Version: 2.1
Name: forch
Version: 0.0.0
Summary: Homemade PyTorch-like Deep Learning framework.
Home-page: https://github.com/songquanpeng/forch
Author: JustSong
Author-email: songquanpeng@foxmail.com
License: MIT
Platform: UNKNOWN
